langchain_text_splitters-1.0.0a1.dist-info/METADATA
langchain_text_splitters-1.0.0a1.dist-info/WHEEL
langchain_text_splitters-1.0.0a1.dist-info/entry_points.txt
langchain_text_splitters/__init__.py
langchain_text_splitters/base.py
langchain_text_splitters/character.py
langchain_text_splitters/html.py
langchain_text_splitters/json.py
langchain_text_splitters/jsx.py
langchain_text_splitters/konlpy.py
langchain_text_splitters/latex.py
langchain_text_splitters/markdown.py
langchain_text_splitters/nltk.py
langchain_text_splitters/py.typed
langchain_text_splitters/python.py
langchain_text_splitters/sentence_transformers.py
langchain_text_splitters/spacy.py
langchain_text_splitters/xsl/converting_to_header.xslt
langchain_text_splitters-1.0.0a1.dist-info/RECORD
