Metadata-Version: 2.1
Name: langchain-text-splitters
Version: 1.0.0a1
Summary: LangChain text splitting utilities
License: MIT
Project-URL: Source Code, https://github.com/langchain-ai/langchain/tree/master/libs/text-splitters
Project-URL: Release Notes, https://github.com/langchain-ai/langchain/releases?q=tag%3A%22langchain-text-splitters%3D%3D0%22&expanded=true
Project-URL: repository, https://github.com/langchain-ai/langchain
Requires-Python: <4.0.0,>=3.10.0
Requires-Dist: langchain-core<2.0.0,>=1.0.0a6
